calculator_pkg/__init__.py
calculator_pkg/config.py
calculator_pkg/service.py
simple_calc_for_api_and_other-0.1.0.dist-info/METADATA
simple_calc_for_api_and_other-0.1.0.dist-info/WHEEL
simple_calc_for_api_and_other-0.1.0.dist-info/top_level.txt
simple_calc_for_api_and_other-0.1.0.dist-info/RECORD
